nibarchive/__init__.py
nibarchive/__main__.py
nibarchive/model.py
nibarchive/parse.py
nibarchive/writer.py
nibarchive-1.1.0.dist-info/LICENSE
nibarchive-1.1.0.dist-info/METADATA
nibarchive-1.1.0.dist-info/WHEEL
nibarchive-1.1.0.dist-info/top_level.txt
nibarchive-1.1.0.dist-info/RECORD
