Metadata-Version: 2.1
Name: nibarchive
Version: 1.1.0
Summary: Parser implementation of NeXTSTEP Interface Builder (NIB) files
Author-email: MatrixEditor <not@supported.com>
Project-URL: Homepage, https://github.com/MatrixEditor/nibarchive
Project-URL: API-Docs, https://matrixeditor.github.io/nibarchive/
Classifier: Development Status :: 5 - Production/Stable
Classifier: Intended Audience :: Science/Research
Classifier: License :: OSI Approved :: GNU General Public License v3 (GPLv3)
Classifier: Programming Language :: Python :: 3.8
Classifier: Programming Language :: Python :: 3.9
Classifier: Programming Language :: Python :: 3.10
License-File: LICENSE
